{"dislike": 0, "spent": 1, "later": 2, "forces?": 3, "greco-bactrian": 4, "war": 5, "central": 6, "wasn't": 7, "whom": 8, "judeans": 9, "any": 10, "grant": 11, "charge": 12, "riding": 13, "armies": 14, "referred": 15, "upgrader": 16, "story": 17, "statement": 18, "state?": 19, "stella": 20, "cemetery": 21, "diplomatic": 22, "while": 23, "every": 24, "north": 25, "ireland": 26, "branch": 27, "asia": 28, "used?": 29, "clotting": 30, "edmonton?": 31, "created": 32, "continental": 33, "african": 34, "christmas": 35, "important": 36, "propaganda": 37, "mines": 38, "title": 39, "started": 40, "cannot": 41, "daughter": 42, "large": 43, "challenges": 44, "come": 45, "mithridates": 46, "living": 47, "stay": 48, "masonry?": 49, "justice": 50, "longer": 51, "lover?": 52, "life": 53, "williams": 54, "part": 55, "code": 56, "africian": 57, "dominated": 58, "uncle,": 59, "battle": 60, "allied": 61, "rhodes": 62, "accounts": 63, "before": 64, "ask": 65, "israel?": 66, "view": 67, "trips?": 68, "it": 69, "public": 70, "mother?": 71, "developed": 72, "how": 73, "start": 74, "officially": 75, "plata?": 76, "prounouncement": 77, "1892?": 78, "founded?": 79, "based": 80, "trading": 81, "introduced": 82, "antipater": 83, "less": 84, "ancient": 85, "election": 86, "estate": 87, "excluded": 88, "plant": 89, "france": 90, "result": 91, "science?": 92, "located?": 93, "visits": 94, "produce": 95, "hellinistic": 96, "manuel": 97, "what": 98, "hand": 99, "amity?": 100, "convert": 101, "company?": 102, "annexed": 103, "made?": 104, "loge": 105, "granted": 106, "city": 107, "develop": 108, "funding": 109, "in?": 110, "volumes": 111, "grandchild": 112, "solis": 113, "rebellion?": 114, "bitumen": 115, "didn't": 116, "initially": 117, "books": 118, "court": 119, "move": 120, "lied": 121, "15": 122, "jerusalem?": 123, "itself": 124, "movie": 125, "investment": 126, "iglesia": 127, "want": 128, "act": 129, "flora": 130, "period?": 131, "place": 132, "led": 133, "del": 134, "split": 135, "territory": 136, "claridge's": 137, "who": 138, "office": 139, "league?": 140, "it's": 141, "into": 142, "voting": 143, "rowan": 144, "entity": 145, "educational": 146, "head": 147, "lived": 148, "british": 149, "gates": 150, "long": 151, "movement?": 152, "india": 153, "scientific": 154, "themselves": 155, "italy": 156, "use": 157, "internationally": 158, "list?": 159, "list": 160, "upon": 161, "rule?": 162, "helped": 163, "flora's": 164, "rights": 165, "leader": 166, "for?": 167, "hills": 168, "line": 169, "met": 170, "upgraders": 171, "he": 172, "foreign": 173, "last?": 174, "montevideo": 175, "another?": 176, "raphia?": 177, "poliorcetes?": 178, "when": 179, "substance": 180, "side": 181, "resigned?": 182, "abscess": 183, "found?": 184, "held?": 185, "freemason": 186, "trust?": 187, "survey": 188, "philip": 189, "carriage": 190, "dynasty?": 191, "been": 192, "lodge": 193, "secretary": 194, "with": 195, "brown": 196, "constitutions": 197, "occupied": 198, "project": 199, "2013?": 200, "coronation?": 201, "rite": 202, "hold?": 203, "cold": 204, "dressed": 205, "brought": 206, "carretas": 207, "leopold": 208, "office?": 209, "who,": 210, "scotland": 211, "charlotte": 212, "queen": 213, "asphalte": 214, "house": 215, "president": 216, "republic?": 217, "charter": 218, "march": 219, "grants": 220, "current": 221, "also": 222, "deposits": 223, "since": 224, "canada": 225, "prince": 226, "rise": 227, "areas": 228, "protestant": 229, "library": 230, "name?": 231, "amity": 232, "school": 233, "uncle": 234, "east": 235, "almost": 236, "held": 237, "death": 238, "her": 239, "buildings": 240, "denied": 241, "coal": 242, "force": 243, "programs?": 244, "reinvent": 245, "garcia": 246, "increase": 247, "buenos": 248, "fall": 249, "israel": 250, "kings": 251, "i": 252, "national": 253, "rumors": 254, "alleged": 255, "no": 256, "oldest": 257, "organic": 258, "history": 259, "father?": 260, "read": 261, "died": 262, "minister": 263, "journals": 264, "divided": 265, "formed?": 266, "constructed": 267, "maclean": 268, "german": 269, "covered": 270, "peel": 271, "war?": 272, "donation": 273, "consist": 274, "far": 275, "blamed": 276, "revolution": 277, "number": 278, "wash": 279, "kind": 280, "castle?": 281, "seven": 282, "rank": 283, "seriously": 284, "ii": 285, "hold": 286, "inaugurated?": 287, "english": 288, "using": 289, "if": 290, "does": 291, "archbishop": 292, "coffin?": 293, "return": 294, "all": 295, "same": 296, "origins": 297, "child?": 298, "call": 299, "body?": 300, "islamic": 301, "power": 302, "india?": 303, "strand": 304, "birth": 305, "replace": 306, "capital": 307, "sometimes": 308, "orsini": 309, "maria": 310, "like": 311, "spend": 312, "challenge": 313, "banned": 314, "spain?": 315, "victoria's": 316, "peace": 317, "class": 318, "lacquer": 319, "and": 320, "promoted": 321, "mix": 322, "commission": 323, "trafalgar": 324, "fructuoso": 325, "based?": 326, "treatment": 327, "received": 328, "robert": 329, "montevideo's": 330, "balmoral": 331, "de": 332, "karim": 333, "uprising": 334, "april": 335, "carried": 336, "master": 337, "founded": 338, "relations": 339, "worshipped": 340, "what?": 341, "jamaica?": 342, "ball": 343, "work": 344, "from?": 345, "documents?": 346, "determine": 347, "where": 348, "occur?": 349, "masonic": 350, "homes": 351, "empress": 352, "iv": 353, "culture?": 354, "anniversary": 355, "whom?": 356, "indian": 357, "marry": 358, "way": 359, "anti-masonry": 360, "canadian": 361, "iii": 362, "found": 363, "political": 364, "own": 365, "form": 366, "whig": 367, "following": 368, "montevideo?": 369, "kent": 370, "hipparchus": 371, "conroy": 372, "happen": 373, "munshi": 374, "shoot": 375, "attempt?": 376, "united": 377, "recognize": 378, "magnesia?": 379, "feel": 380, "replaced": 381, "words": 382, "lost": 383, "deraismes": 384, "ireland?": 385, "focus": 386, "father": 387, "located": 388, "tories": 389, "star": 390, "england": 391, "aggregates?": 392, "more": 393, "greece?": 394, "stairs?": 395, "inhabitants": 396, "golan": 397, "eighth": 398, "short": 399, "raised": 400, "forms": 401, "famous": 402, "mother": 403, "go": 404, "membership": 405, "rome": 406, "military?": 407, "melbourne": 408, "well": 409, "each": 410, "by": 411, "created?": 412, "concrete": 413, "2009?": 414, "produce?": 415, "empire?": 416, "support": 417, "treat": 418, "jurisdiction": 419, "visit?": 420, "placed": 421, "required": 422, "freemasonry": 423, "suffer": 424, "them": 425, "defeat": 426, "disraeli's": 427, "on?": 428, "year?": 429, "focused": 430, "census": 431, "former": 432, "synthetic": 433, "best": 434, "university?": 435, "happened": 436, "him": 437, "reason": 438, "bank": 439, "be": 440, "some": 441, "anti-masonics": 442, "government": 443, "declared": 444, "trying": 445, "specifically": 446, "health": 447, "theater?": 448, "oxford": 449, "women": 450, "children": 451, "iii?": 452, "date": 453, "thought": 454, "religion": 455, "arab": 456, "patent": 457, "taranco": 458, "responsible": 459, "fire": 460, "petroleum": 461, "pennsylvania": 462, "who's": 463, "napoleon": 464, "order": 465, "are": 466, "ijm": 467, "after": 468, "temperatures": 469, "corinth?": 470, "mother's": 471, "several": 472, "park": 473, "date?": 474, "leading": 475, "invade": 476, "used": 477, "over": 478, "marriage": 479, "clipsas": 480, "left": 481, "product": 482, "queens": 483, "sold": 484, "they": 485, "port": 486, "selenizza": 487, "albanian": 488, "guests": 489, "in": 490, "person": 491, "take": 492, "spain": 493, "oribe": 494, "technology": 495, "life?": 496, "formation": 497, "v": 498, "clark": 499, "russell": 500, "duke": 501, "successor": 502, "inherit": 503, "isolated": 504, "established": 505, "diesel": 506, "daughters": 507, "division": 508, "represented": 509, "oil": 510, "himself": 511, "fail": 512, "street": 513, "besides": 514, "theater": 515, "with?": 516, "female": 517, "get": 518, "included": 519, "1948": 520, "many": 521, "would": 522, "meet": 523, "oils": 524, "relationship": 525, "remains": 526, "southern": 527, "disraeli": 528, "time": 529, "assassinate": 530, "melinda": 531, "america": 532, "million": 533, "paint": 534, "constructed?": 535, "whose": 536, "supported": 537, "prime": 538, "us": 539, "material": 540, "only": 541, "simsa": 542, "people?": 543, "previously": 544, "scythians": 545, "relief?": 546, "provincial": 547, "civil": 548, "require": 549, "provide": 550, "bedchamber": 551, "space": 552, "31": 553, "other": 554, "deposits?": 555, "single": 556, "anaesthetic": 557, "came": 558, "very": 559, "usually": 560, "years": 561, "israeli": 562, "asphalt?": 563, "alberta?": 564, "uruguayan": 565, "similar": 566, "zeus": 567, "light": 568, "freemason?": 569, "launch": 570, "reforms": 571, "having": 572, "canada's": 573, "can": 574, "taken": 575, "until": 576, "art?": 577, "britains": 578, "accused": 579, "movement": 580, "makes": 581, "rodo": 582, "leopold?": 583, "don't": 584, "pitch": 585, "republic": 586, "members": 587, "into?": 588, "oa": 589, "herself": 590, "estadio": 591, "gas": 592, "\"pregnancy\"?": 593, "first": 594, "france?": 595, "jubilee?": 596, "edward": 597, "atheists?": 598, "1": 599, "visit": 600, "times?": 601, "conroy?": 602, "foundation": 603, "play": 604, "see": 605, "declare": 606, "philippe": 607, "must": 608, "complain": 609, "paired": 610, "aim": 611, "rio": 612, "constitution?": 613, "family": 614, "la": 615, "ii?": 616, "assasination": 617, "need": 618, "world's": 619, "START": 620, "1880?": 621, "retire?": 622, "save": 623, "business": 624, "times": 625, "grand": 626, "shares": 627, "what's": 628, "whigs?": 629, "2004,": 630, "wanted": 631, "1858?": 632, "ort": 633, "post": 634, "degree": 635, "golden": 636, "lodges": 637, "from": 638, "establish": 639, "greeks": 640, "youngest": 641, "scandal": 642, "percent": 643, "geographical": 644, "18th": 645, "policies": 646, "century": 647, "syrian": 648, "face": 649, "their": 650, "major": 651, "crude": 652, "called": 653, "decide": 654, "occur": 655, "muslims": 656, "2013": 657, "attempted": 658, "19th": 659, "an": 660, "built?": 661, "assasinate": 662, "population": 663, "death?": 664, "university": 665, "average": 666, "windsor?": 667, "achieve": 668, "old": 669, "parque": 670, "settle": 671, "core": 672, "paving": 673, "bring": 674, "recieved": 675, "did": 676, "popular": 677, "armenia": 678, "describe": 679, "appointed": 680, "oil?": 681, "known?": 682, "seleucid": 683, "refuse": 684, "father's": 685, "boer": 686, "associated": 687, "make": 688, "changed": 689, "potato": 690, "lose": 691, "financial": 692, "up": 693, "seen": 694, "defense": 695, "objection": 696, "wsh": 697, "type": 698, "state": 699, "lodge?": 700, "END": 701, "education": 702, "literary": 703, "carriers": 704, "?": 705, "seleucus": 706, "assume": 707, "jurisdiction?": 708, "princess": 709, "passwords": 710, "irish": 711, "wedding": 712, "military": 713, "word": 714, "its": 715, "museum": 716, "ptolemaic": 717, "russo-turkish": 718, "reign": 719, "married?": 720, "won": 721, "jews": 722, "final": 723, "most": 724, "art": 725, "peninsula?": 726, "removed": 727, "river": 728, "largest": 729, "basic": 730, "security": 731, "supply": 732, "general": 733, "trip": 734, "began": 735, "swear": 736, "deposit": 737, "style": 738, "on": 739, "rock": 740, "country": 741, "improve": 742, "cover?": 743, "saw": 744, "show": 745, "2012?": 746, "proposed": 747, "entered": 748, "fought": 749, "greatest": 750, "conflict": 751, "half": 752, "constitution": 753, "spanish": 754, "ptolemy?": 755, "cannae?": 756, "fight": 757, "relations?": 758, "ended": 759, "church": 760, "world": 761, "rituals": 762, "kindest": 763, "try": 764, "palace": 765, "help": 766, "stance": 767, "between?": 768, "forgotten?": 769, "wales": 770, "made": 771, "mastic": 772, "live": 773, "types": 774, "world?": 775, "shell": 776, "join": 777, "wives": 778, "beginning": 779, "minister?": 780, "gave": 781, "interest": 782, "ranked": 783, "administrative": 784, "captured": 785, "berkshire": 786, "issued": 787, "disease": 788, "there?": 789, "groups": 790, "official": 791, "journal?": 792, "main": 793, "ladies": 794, "inquiry": 795, "encouraged": 796, "opened": 797, "des": 798, "as?": 799, "egypt?": 800, "honor": 801, "natural": 802, "resign?": 803, "top": 804, "working": 805, "increased": 806, "annoyed": 807, "mostly": 808, "blame": 809, "army": 810, "statue": 811, "one": 812, "donated": 813, "company": 814, "lady": 815, "practice": 816, "be?": 817, "rule": 818, "languages": 819, "data": 820, "mason": 821, "famine": 822, "region": 823, "painted": 824, "macedonian": 825, "nearly": 826, "history?": 827, "considered": 828, "religion?": 829, "maclean's": 830, "to?": 831, "age": 832, "a": 833, "temple": 834, "have": 835, "son": 836, "cause": 837, "her?": 838, "turn": 839, "there": 840, "museo": 841, "against": 842, "2015?": 843, "being": 844, "energy": 845, "added": 846, "roads": 847, "separate": 848, "matter": 849, "under": 850, "unlawful": 851, "receive": 852, "higher": 853, "avenue": 854, "church?": 855, "policy": 856, "another": 857, "punta": 858, "took": 859, "majority": 860, "roman": 861, "unofficial": 862, "three": 863, "football": 864, "us?": 865, "great": 866, "empire": 867, "england?": 868, "college": 869, "blight": 870, "ally": 871, "book": 872, "countries": 873, "throne": 874, "iraq": 875, "subsidiary": 876, "end": 877, "opposed": 878, "road": 879, "written": 880, "shot": 881, "tar": 882, "said": 883, "country?": 884, "production?": 885, "leader?": 886, "uruguay's": 887, "pontus": 888, "rumored": 889, "queen?": 890, "palmerston?": 891, "spread": 892, "israelis": 893, "aid": 894, "country's": 895, "begin": 896, "hellenistic": 897, "orient": 898, "hastings": 899, "mainly": 900, "around": 901, "big": 902, "term": 903, "established?": 904, "stop": 905, "settled": 906, "pavement?": 907, "festival": 908, "victoria": 909, "palmerston": 910, "belief": 911, "anti-masonic": 912, "party": 913, "athens?": 914, "end?": 915, "uruguay": 916, "beatrice": 917, "greek": 918, "commons?": 919, "consider": 920, "event": 921, "monarch": 922, "which": 923, "monarchy": 924, "set": 925, "albert": 926, "confused": 927, "jewish": 928, "foot": 929, "do": 930, "immigrants": 931, "middle": 932, "nazi": 933, "had": 934, "nickname": 935, "during": 936, "were": 937, "could": 938, "brothers": 939, "private": 940, "conquered": 941, "victoria?": 942, "john": 943, "candidate": 944, "spoke": 945, "american": 946, "these": 947, "open": 948, "pergamum": 949, "prior": 950, "has": 951, "gladstone": 952, "d'italia": 953, "printed": 954, "withdraw": 955, "action": 956, "independence?": 957, "born?": 958, "ptolemy": 959, "states?": 960, "birth?": 961, "differences": 962, "allowed": 963, "things": 964, "alexander?": 965, "maris": 966, "defeated?": 967, "sir": 968, "toilet": 969, "mandatory": 970, "concerns": 971, "alexander's": 972, "antiochus": 973, "royal": 974, "osborne": 975, "power?": 976, "impact": 977, "write": 978, "children?": 979, "wrote": 980, "wars?": 981, "became": 982, "papal": 983, "usual": 984, "area": 985, "culture": 986, "point": 987, "actually": 988, "defeated": 989, "to": 990, "invited": 991, "promote": 992, "do?": 993, "trust": 994, "exposure": 995, "throne?": 996, "taking": 997, "donate": 998, "uruguay?": 999, "mixed": 1000, "center": 1001, "percentage": 1002, "companies": 1003, "published": 1004, "common": 1005, "region?": 1006, "announce": 1007, "early": 1008, "palacio": 1009, "craft": 1010, "initial": 1011, "nuclear": 1012, "gaza": 1013, "reigning": 1014, "july": 1015, "london?": 1016, "period": 1017, "developing": 1018, "over-lapping": 1019, "instead": 1020, "law": 1021, "visited": 1022, "returned": 1023, "destroyed": 1024, "language": 1025, "give": 1026, "name": 1027, "global": 1028, "candidates": 1029, "born": 1030, "lack": 1031, "writer": 1032, "zionism?": 1033, "system?": 1034, "pass": 1035, "amount": 1036, "bill": 1037, "risk?": 1038, "low": 1039, "y": 1040, "napoleon?": 1041, "different": 1042, "between": 1043, "will": 1044, "leave": 1045, "local": 1046, "position": 1047, "judea": 1048, "exclusive": 1049, "ill": 1050, "or": 1051, "freemasons?": 1052, "making": 1053, "plants": 1054, "masons": 1055, "rally": 1056, "ago": 1057, "citizens": 1058, "kingdom": 1059, "egypt": 1060, "died?": 1061, "attack": 1062, "i?": 1063, "group": 1064, "mean?": 1065, "batlle": 1066, "allow": 1067, "forced": 1068, "use?": 1069, "french": 1070, "alexander": 1071, "who?": 1072, "program": 1073, "century?": 1074, "full": 1075, "have?": 1076, "victorias": 1077, "by?": 1078, "studies": 1079, "population?": 1080, "sands": 1081, "biography": 1082, "trade": 1083, "differ": 1084, "crisis": 1085, "canterbury": 1086, "lantern": 1087, "fund": 1088, "dissolved": 1089, "invaded": 1090, "high": 1091, "at": 1092, "body": 1093, "reign?": 1094, "10": 1095, "advised": 1096, "ruled": 1097, "known": 1098, "indo-greek": 1099, "area?": 1100, "blood": 1101, "recognition": 1102, "work?": 1103, "designed": 1104, "of?": 1105, "demetrius": 1106, "control": 1107, "freemasons": 1108, "not": 1109, "outside": 1110, "tall": 1111, "but": 1112, "ugle": 1113, "two": 1114, "link": 1115, "emulsions": 1116, "example": 1117, "menander": 1118, "britain": 1119, "jose": 1120, "israel's": 1121, "purchase": 1122, "days": 1123, "gods": 1124, "as": 1125, "lodge,": 1126, "development": 1127, "republica": 1128, "order?": 1129, "halt": 1130, "per": 1131, "say": 1132, "when?": 1133, "built": 1134, "2011": 1135, "composed": 1136, "regime?": 1137, "industry": 1138, "originally": 1139, "catholic": 1140, "francis": 1141, "down": 1142, "ministry?": 1143, "dynasty": 1144, "marry?": 1145, "efforts": 1146, "system": 1147, "believe": 1148, "feature": 1149, "earliest": 1150, "lodges?": 1151, "states": 1152, "the": 1153, "maccabean": 1154, "worst": 1155, "black": 1156, "crimean": 1157, "egyptian": 1158, "tons": 1159, "assassination": 1160, "warren": 1161, "alberts": 1162, "about": 1163, "kingdom?": 1164, "gladstone?": 1165, "accept": 1166, "lord": 1167, "than": 1168, "never": 1169, "craft?": 1170, "childbirth?": 1171, "1900?": 1172, "appear": 1173, "research": 1174, "law?": 1175, "money": 1176, "greatly": 1177, "tried": 1178, "always": 1179, "ruler": 1180, "sentence": 1181, "historians": 1182, "army?": 1183, "poliorcetes": 1184, "teach": 1185, "called?": 1186, "academic": 1187, "may": 1188, "greece": 1189, "centre": 1190, "secrets": 1191, "resign": 1192, "hathaway": 1193, "albert?": 1194, "day": 1195, "appoint": 1196, "believed": 1197, "third": 1198, "purchased?": 1199, "manservent": 1200, "nabatean": 1201, "league": 1202, "married": 1203, "unit": 1204, "free": 1205, "given": 1206, "resigned": 1207, "oil,": 1208, "mamluk": 1209, "color": 1210, "his": 1211, "organization": 1212, "institute": 1213, "was": 1214, "back": 1215, "mothers": 1216, "canon": 1217, "torres": 1218, "legal": 1219, "launched": 1220, "greater": 1221, "athabasca": 1222, "metropolitan": 1223, "coronation": 1224, "concept": 1225, "goal": 1226, "seeking": 1227, "barrels": 1228, "occurring": 1229, "oppose": 1230, "dr.": 1231, "put": 1232, "hall": 1233, "george": 1234, "polybius": 1235, "magazine": 1236, "that": 1237, "asphalt": 1238, "17?": 1239, "people": 1240, "now": 1241, "treated": 1242, "paved": 1243, "year": 1244, "disclosure": 1245, "louis": 1246, "air": 1247, "where?": 1248, "planned": 1249, "caused": 1250, "supreme": 1251, "international": 1252, "destroy": 1253, "york": 1254, "else": 1255, "sands?": 1256, "due": 1257, "oath": 1258, "for": 1259, "language?": 1260, "claridge": 1261, "construction": 1262, "public?": 1263, "rules": 1264, "investments": 1265, "heat": 1266, "without": 1267, "formed": 1268, "become": 1269, "annual": 1270, "man": 1271, "killed": 1272, "christian": 1273, "share": 1274, "both": 1275, "smallest": 1276, "exist": 1277, "king": 1278, "voted": 1279, "of": 1280, "along": 1281, "think": 1282, "scottish": 1283, "purpose": 1284, "albert's": 1285, "water": 1286, "second": 1287, "influence": 1288, "laid": 1289, "west": 1290, "up?": 1291, "refusal": 1292, "antigonus": 1293, "title?": 1294, "much": 1295, "dense": 1296, "freemasonry?": 1297, "die?": 1298, "through": 1299, " PAD ": 1300, "june": 1301, "schools": 1302, "hot": 1303, "issue": 1304, "building": 1305, "antikythera": 1306, "home": 1307, "find": 1308, "brown?": 1309, "succession": 1310, "funeral": 1311, "dutchess": 1312, "comprised": 1313, "member": 1314, "artist": 1315, "accepted": 1316, "lead": 1317, "last": 1318, "god?": 1319, "derby": 1320, "diadochi": 1321, "she": 1322, "begin?": 1323, "lower": 1324, "degrees": 1325, "attempt": 1326, "famine?": 1327, "few": 1328, "palestine?": 1329, "land": 1330, "according": 1331, "is": 1332, "sicily": 1333, "production": 1334, "\"the": 1335, "cabildo": 1336, "london": 1337, "americans?": 1338, "so": 1339, "new": 1340, "access": 1341, "iraq?": 1342, "why": 1343, "bce?": 1344, "america?": 1345, "produced": 1346, "accepts": 1347, "bitumen?": 1348, "b?": 1349, "removal": 1350, "daughter?": 1351, "because": 1352, "orthodox": 1353, "jubilee": 1354, "closest": 1355, "god": 1356, "happens": 1357, "square?": 1358, "over?": 1359, "william": 1360, "often": 1361, "out": 1362, "among": 1363, "process": 1364}