{"symbiotic": 0, "focus": 1, "involved": 2, "amount": 3, "damage": 4, "located": 5, "archive?": 6, "prevents": 7, "low": 8, "military": 9, "17th": 10, "operation": 11, "forces?": 12, "its": 13, "word": 14, "defence": 15, "war": 16, "scientology": 17, "stadtholders": 18, "wasn't": 19, "aren't": 20, "utrecht": 21, "more": 22, "essential": 23, "rangers": 24, "between": 25, "will": 26, "any": 27, "leave": 28, "keep": 29, "should": 30, "most": 31, "netbula": 32, "or": 33, "division?": 34, "removed": 35, "elect": 36, "plants": 37, "kinds": 38, "record": 39, "units": 40, "famous": 41, "influenced": 42, "canadians": 43, "kingdom": 44, "go": 45, "2002?": 46, "princes": 47, "forces": 48, "rome": 49, "military?": 50, "internet": 51, "intervals": 52, "stand": 53, "roles": 54, "general": 55, "each": 56, "echostar's": 57, "trent": 58, "by": 59, "created": 60, "condition": 61, "affect": 62, "group": 63, "important": 64, "empire?": 65, "support": 66, "applied": 67, "small": 68, "demonstrates": 69, "on": 70, "follmer": 71, "country": 72, "rate": 73, "parts": 74, "jurisdiction": 75, "content?": 76, "large": 77, "henry": 78, "pius": 79, "laws": 80, "french": 81, "century?": 82, "come": 83, "have?": 84, "by?": 85, "cardinals?": 86, "living": 87, "heads": 88, "version": 89, "stock": 90, "show": 91, "eventually": 92, "provinces": 93, "trade": 94, "them": 95, "ectoparasites": 96, "on?": 97, "year?": 98, "part": 99, "sites?": 100, "california's": 101, "chief": 102, "at": 103, "regarding": 104, "site?": 105, "defence?": 106, "battle": 107, "lives": 108, "original": 109, "copies": 110, "ruled": 111, "directory": 112, "interaction": 113, "known": 114, "actor": 115, "county": 116, "be": 117, "organism": 118, "past": 119, "before": 120, "holland": 121, "some": 122, "government": 123, "naval": 124, "commander": 125, "spanish": 126, "trying": 127, "treaty": 128, "it": 129, "public": 130, "content": 131, "how": 132, "of?": 133, "record?": 134, "coats": 135, "further": 136, "include": 137, "subject": 138, "certain": 139, "data?": 140, "control": 141, "church": 142, "plants?": 143, "health": 144, "world": 145, "status": 146, "\"symbiosis\"": 147, "brigades": 148, "alter": 149, "sent": 150, "not": 151, "surface": 152, "women": 153, "squadron": 154, "date": 155, "outside": 156, "based": 157, "but": 158, "define": 159, "case": 160, "two": 161, "operate?": 162, "training": 163, "patent": 164, "symbiosis": 165, "example": 166, "stated": 167, "available": 168, "wayback": 169, "france": 170, "responsible": 171, "located?": 172, "joint": 173, "eligible": 174, "doesn't": 175, "made": 176, "requirement": 177, "as": 178, "produce": 179, "strong": 180, "live": 181, "order": 182, "what": 183, "are": 184, "priests": 185, "men": 186, "after": 187, "machine": 188, "wear": 189, "several": 190, "bary": 191, "temporarily": 192, "estimated": 193, "dmca": 194, "beginning": 195, "gave": 196, "british?": 197, "develop": 198, "suit": 199, "platform": 200, "upgrade": 201, "shrimp": 202, "bacteria": 203, "border": 204, "in?": 205, "responsibility": 206, "used": 207, "over": 208, "ritteri": 209, "there?": 210, "fungi": 211, "filed": 212, "official": 213, "main": 214, "they": 215, "offices": 216, "republican": 217, "opened": 218, "didn't": 219, "system": 220, "initially": 221, "court": 222, "believe": 223, "bee": 224, "union?": 225, "as?": 226, "robots.txt": 227, "file?": 228, "in": 229, "person": 230, "reformed": 231, "take": 232, "europe?": 233, "effort": 234, "sign": 235, "states": 236, "want": 237, "the": 238, "formation": 239, "&": 240, "uniform": 241, "act": 242, "place": 243, "led": 244, "army": 245, "duke": 246, "assigned?": 247, "one": 248, "company": 249, "travel": 250, "portugese": 251, "other?": 252, "rule": 253, "services": 254, "about": 255, "who": 256, "be?": 257, "office": 258, "revolt": 259, "cell": 260, "into": 261, "tree": 262, "data": 263, "persecution": 264, "uniform?": 265, "organisms": 266, "scientists": 267, "systems?": 268, "accept": 269, "opening": 270, "head": 271, "bruce": 272, "than": 273, "holy": 274, "never": 275, "url": 276, "with?": 277, "appear": 278, "considered": 279, "get": 280, "reserve": 281, "many": 282, "orders": 283, "would": 284, "to?": 285, "long": 286, "movement?": 287, "age": 288, "a": 289, "have": 290, "advocates": 291, "years?": 292, "relationship": 293, "always": 294, "religious": 295, "use": 296, "there": 297, "protect?": 298, "size": 299, "time": 300, "endosymbiont": 301, "anjou": 302, "cardinal": 303, "saved": 304, "dutch": 305, "army?": 306, "against": 307, "upon": 308, "being": 309, "right": 310, "supposed": 311, "symbiosis?": 312, "testing?": 313, "called?": 314, "released": 315, "task": 316, "aided": 317, "under": 318, "compared": 319, "for?": 320, "appoint": 321, "whose": 322, "relationship?": 323, "another": 324, "us": 325, "site": 326, "stored": 327, "material": 328, "roman": 329, "only": 330, "takes": 331, "women?": 332, "secretary-in-chief": 333, "when": 334, "declaration": 335, "cities": 336, "pope": 337, "study": 338, "caf?": 339, "ultimate": 340, "within": 341, "great": 342, "council": 343, "union": 344, "federal": 345, "empire": 346, "free": 347, "host": 348, "college": 349, "england?": 350, "clownfish": 351, "cansofcom": 352, "given": 353, "it?": 354, "countries": 355, "orange?": 356, "this": 357, "philip": 358, "provide": 359, "counterclaims": 360, "been": 361, "other": 362, "europe": 363, "with": 364, "zeeland": 365, "command": 366, "shell's": 367, "was": 368, "telewizja": 369, "back": 370, "cold": 371, "completed": 372, "species": 373, "years": 374, "kaplan": 375, "navy": 376, "chosen": 377, "fish?": 378, "depend": 379, "california": 380, "keeping": 381, "vi": 382, "aid": 383, "information": 384, "asian": 385, "protect": 386, "sites": 387, "operate": 388, "gives": 389, "similar": 390, "available?": 391, "republic?": 392, "current": 393, "also": 394, "latin": 395, "that": 396, "term": 397, "canada": 398, "since": 399, "established?": 400, "people": 401, "rise": 402, "healthcare": 403, "hermit": 404, "direct": 405, "equipment": 406, "having": 407, "currently": 408, "year": 409, "ecumenical": 410, "parasitic": 411, "overseas": 412, "canada's": 413, "air": 414, "can": 415, "taken": 416, "until": 417, "netherlands?": 418, "banning": 419, "stationed?": 420, "force?": 421, "root": 422, "party": 423, "size?": 424, "international": 425, "assassinated?": 426, "held": 427, "necessary": 428, "republic": 429, "symbionts?": 430, "approximately": 431, "holland?": 432, "machine?": 433, "total": 434, "end?": 435, "jobs": 436, "members": 437, "denied": 438, "force": 439, "for": 440, "machine's": 441, "pages": 442, "increase": 443, "survive": 444, "provide?": 445, "rules": 446, "event": 447, "which": 448, "first": 449, "batavian": 450, "endosymbionts": 451, "national": 452, "goby": 453, "without": 454, "france?": 455, "caf": 456, "mycorrhyzal": 457, "become": 458, "no": 459, "wide": 460, "oldest": 461, "do": 462, "operations": 463, "gain": 464, "had": 465, "during": 466, "were": 467, "commander-in-chief": 468, "file": 469, "paul": 470, "netherlands": 471, "locations?": 472, "could": 473, "specific": 474, "private": 475, "territories": 476, "animals": 477, "both": 478, "must": 479, "archive's": 480, "war?": 481, "american": 482, "armed": 483, "rocky": 484, "these": 485, "open": 486, "signed?": 487, "names": 488, "consist": 489, "snapshots": 490, "v.": 491, "off": 492, "has": 493, "of": 494, "provinces?": 495, "obligate": 496, "web?": 497, "number": 498, "kind": 499, "non-canadian": 500, "assigned": 501, "ii?": 502, "comments": 503, "definition": 504, "anton": 505, "organized": 506, "cardinals": 507, "need": 508, "members?": 509, "troops": 510, "influence": 511, "wars": 512, "START": 513, "controversy": 514, "ibex": 515, "strategy": 516, "ii": 517, "rome?": 518, "permitted": 519, "countries?": 520, "save": 521, "individuals": 522, "if": 523, "does": 524, "suzanne": 525, "much": 526, "chordiant": 527, "through": 528, " PAD ": 529, "allowed": 530, "evolution?": 531, "evidence?": 532, "canada?": 533, "afghanistan?": 534, "sea": 535, "all": 536, "discovered?": 537, "same": 538, "wanted": 539, "independence": 540, "\"cardinal\"": 541, "critical": 542, "command?": 543, "power": 544, "nutrients": 545, "replace": 546, "crab": 547, "royal": 548, "heinrich": 549, "from": 550, "special": 551, "percent": 552, "still": 553, "and": 554, "utrecht?": 555, "century": 556, "their": 557, "website?": 558, "case?": 559, "major": 560, "serve": 561, "orange": 562, "called": 563, "last": 564, "start?": 565, "worn": 566, "became": 567, "churches?": 568, "management": 569, "de": 570, "an": 571, "nato": 572, "founded": 573, "place?": 574, "present": 575, "to": 576, "time?": 577, "what?": 578, "won't": 579, "from?": 580, "block": 581, "can't": 582, "where": 583, "is": 584, "exchange": 585, "recruited": 586, "judge": 587, "canadian": 588, "did": 589, "new": 590, "components": 591, "iii": 592, "serve?": 593, "early": 594, "web": 595, "describe": 596, "fish": 597, "iraq?": 598, "why": 599, "relationships": 600, "requested": 601, "inclusion": 602, "them?": 603, "contribute": 604, "make": 605, "up": 606, "period": 607, "down?": 608, "minor": 609, "host?": 610, "websites": 611, "netbula's": 612, "type": 613, "location": 614, "happens": 615, "state": 616, "united": 617, "william": 618, "refugees": 619, "law": 620, "bacteria?": 621, "described": 622, "END": 623, "give": 624, "name": 625, "out": 626, "archive": 627, "replaced": 628, "among": 629}