{"<a": 0, "why": 1, "are": 2, "your": 3, "it": 4, "how": 5, "for": 6, "never.": 7, "say": 8, "if": 9, "than": 10, "chuck": 11, "never": 12, "is": 13, "sometimes.": 14, "know.": 15, "that": 16, "better": 17, " PAD ": 18, "me": 19, "and": 20, "not": 21, "you": 22, "i": 23, "the": 24, "with": 25, "he": 26, "of": 27, "am": 28, "would": 29, "but": 30, "long": 31, "know": 32, "only": 33, "more": 34, "a": 35, "ever": 36, "was": 37, "one": 38, "please": 39, "can": 40, "question": 41, "everything.": 42, "be.": 43, "tell": 44, "bartender": 45, "time.": 46, "about": 47, "me.": 48, "END": 49, "START": 50, "now.": 51, "don't": 52, "being": 53, "what": 54, "to": 55}