{"here": 0, "an": 1, "the": 243, "question.": 4, "entitled": 2, "sense": 7, "people": 8, "ask": 10, "like": 11, "not?": 13, "now": 14, "good.": 15, "love?": 16, "again": 17, "have": 18, "nice": 19, "need": 21, "sure,": 167, "-": 23, "joke": 24, "beginning,": 25, "lot": 5, "solar": 26, "sorry.": 27, "full": 28, "often": 246, "now.": 29, "should": 30, "more": 31, "never": 6, "power?": 32, "ha!": 33, "perhaps": 34, "answer.": 35, "course": 36, "too.": 37, "too!": 39, "let's": 40, "did.": 41, "another": 42, "would": 9, "there": 48, "what's": 44, "yes,": 45, "enough": 46, "mean.": 50, "question?": 293, " PAD ": 49, "do": 51, "who": 52, "happy": 69, "your": 53, "mind.": 54, "physics?": 55, "please.": 56, "on": 12, "...": 174, "that?": 60, "memory.": 63, "other": 62, "up": 325, "understand.": 64, "and": 65, "why": 66, "some": 68, "confused!": 181, "<a": 70, "say.": 72, "pardon": 71, "come": 73, "try": 74, "computer.": 75, "think": 295, "few": 76, "better.": 77, "give": 263, "person.": 177, "makes": 78, "hard": 312, "poetry?": 79, "by": 3, "one": 239, "that.": 285, "years": 80, "pretty": 22, "more.": 81, "isn't": 82, "friends": 83, "find": 88, "aren't": 85, "here!</a>": 86, "it.": 87, "are.": 294, "really?": 90, "words": 248, "say": 296, "really": 93, "when": 94, "am": 95, "at": 96, "all": 262, "no.": 20, "talking": 238, "chatting": 299, "thing": 277, "may": 98, "favourite": 301, "explain.": 99, "first": 100, "for": 102, "tell": 103, "it?": 104, "happy.": 105, "me": 250, "mean": 187, "told": 106, "that!": 186, "get": 107, "explain": 108, "does": 109, "best": 111, "keep": 118, "must": 114, "work": 116, "already": 119, "target=\"_blank\">click": 304, "what": 120, "three": 121, "nobody": 122, "married.": 123, "right": 124, "life.": 125, "prove": 126, "then": 320, "about.": 256, "clear": 127, "how": 191, "poetry": 128, "what?": 130, "most": 129, "something": 113, "any": 131, "of": 132, "you": 133, "are": 134, "understand": 318, "END": 135, "who?": 219, "about?": 136, "people.": 331, "this": 137, "won't": 138, "question": 140, "much?": 149, "my": 141, "doing": 147, "you?": 145, "not": 257, "everything": 148, "but": 151, "bible.": 159, "ever": 154, "with": 153, "anything": 156, "really.": 283, "that's": 157, "ha": 321, "or": 160, "a": 161, "chuck": 162, "know": 163, "in": 244, "answer": 164, "well,": 249, "has": 165, "make": 166, "to": 168, "really!": 172, "sure?": 170, "good": 171, "love": 175, "ok": 176, "thank": 84, "sure": 178, "i'm": 139, "change": 180, "thought": 182, "am.": 266, "everything.": 184, "do.": 185, "chatbot.": 189, "see.": 218, "that": 190, "nice.": 183, "long": 193, "were": 251, "forever": 194, "no,": 195, "ok,": 196, "shall": 197, "know?": 198, "time": 203, "don't": 200, "they": 89, "certain": 202, "out": 38, "think.": 258, "well": 204, "though.": 268, "go": 205, "no": 67, "robot.": 207, "quite": 291, "oh,": 112, "know.": 212, "mean?": 216, "can't": 214, "old.": 215, "did": 217, "lot.": 221, "from": 179, "one?": 220, "could": 222, "little": 92, "still": 225, "looking": 226, "interesting.": 227, "bit": 210, "go.": 229, "because": 230, "its": 232, "me.": 206, "even": 143, "glad": 313, "if": 234, "alone.": 235, "prefer": 208, "computer": 57, "human?": 236, "friend.": 237, "sense.": 97, "where": 146, "change.": 241, "intelligent": 242, "many": 231, "second": 308, "so": 142, "says": 247, "human.": 115, "had": 61, "you,": 211, "one.": 173, "maybe": 322, "always": 252, "again.": 255, "seem": 335, "see": 144, "hope": 259, "we": 260, "cannot": 261, "only": 43, "then?": 264, "it": 265, "questions.": 199, "16": 267, "please": 269, "matter": 47, "chat": 323, "too": 270, "talk": 271, "know,": 302, "real": 272, "interested": 273, "about": 150, "knows": 240, "am?": 101, "being": 316, "human": 152, "really,": 274, "just": 280, "to?": 281, "out.": 188, "was": 275, "bible?": 284, "yourself": 224, "you.": 328, "last": 286, "way": 276, "good!": 287, "is": 169, "than": 288, "guess": 289, "me?": 290, "sure.": 223, "START": 292, "to.": 155, "born": 279, "can": 201, "things": 297, "it's": 298, "sound": 253, "now?": 300, "ok.": 278, "left": 332, "think?": 303, "under": 305, "made": 306, "might": 307, "means": 59, "you!": 309, "want": 333, "much": 254, "i": 310, "bored": 245, "doesn't": 314, "bad.": 315, "will": 317, "course.": 228, "didn't": 319, "sounds": 192, "sometimes": 91, "yes.": 282, "so,": 233, "were.": 324, "time.": 326, "rather": 213, "you're": 327, "be": 117, "feel": 329, "very": 330, "yourself.": 311, "someone": 110, "remember": 334, "as": 336, "sorry,": 209, "is.": 158, "yes": 58}