{"0": "why", "1": "are", "2": "something", "3": "explain.", "4": "understand.", "5": ".", "6": "human.", "7": "in", "8": "you're", "9": "this", "10": "talking", "11": "explain", "12": "is", "13": "about?", "14": "that", "15": "i'm", "16": " PAD ", "17": "me", "18": "my", "19": "and", "20": "not", "21": "you", "22": "shall", "23": "i", "24": "the", "25": "to", "26": "with", "27": "of", "28": "am", "29": "now", "30": "at", "31": "very", "32": "know", "33": "a", "34": "you?", "35": "thank", "36": "have", "37": "please", "38": "so", "39": "longest", "40": "do", "41": "be", "42": "or", "43": "tell", "44": "about", "45": "answer", "46": "you.", "47": "END", "48": "START", "49": "don't", "50": "being", "51": "like", "52": "what", "53": "it"}